levelflatten/README.MD
levelflatten/__init__.py
levelflatten/requirements.txt
levelflatten/thirdparty.json
levelflatten-0.10.dist-info/LICENSE.rst
levelflatten-0.10.dist-info/METADATA
levelflatten-0.10.dist-info/WHEEL
levelflatten-0.10.dist-info/top_level.txt
levelflatten-0.10.dist-info/RECORD
