Metadata-Version: 2.1
Name: levelflatten
Version: 0.10
Summary: performs customizable level-wise flattening of nested iterables.
Home-page: https://github.com/hansalemaos/levelflatten
Author: Johannes Fischer
Author-email: aulasparticularesdealemaosp@gmail.com
License: MIT
Keywords: nested iterables,flatten
Classifier: Development Status :: 4 - Beta
Classifier: Programming Language :: Python :: 3 :: Only
Classifier: Programming Language :: Python :: 3.10
Classifier: Topic :: Software Development :: Libraries :: Python Modules
Classifier: Topic :: Utilities
License-File: LICENSE.rst
Requires-Dist: isiter
Requires-Dist: tolerant-isinstance
